{
    "code": "raNum17",
    "meta": {},
    "title": "Racionaliza la siguiente expresión.",
    "text": "Realiza la división de radicales y escribe su resultado.",
    "initialExpression": "\\frac{1}{\\sqrt{3}}",
    "type": "lvltutor",
    "steps": [
        {
            "stepId": "0",
            "stepTitle": "Para este caso, identifica el denominador radical.",
            "expression": "\\frac{1}{\\sqrt{3}}",
            "KCs": [
                "IdeDenoRadi"
            ],
            "hints": [
                {
                    "hintId": 0,
                    "hint": "Para racionalizar, necesitas identificar correctamente el denominador radical. Por ejemplo :  ",
                    "expression": "\\frac{a}{\\sqrt{b}} \\longrightarrow \\sqrt{b}"
                },
                {
                    "hintId": 1,
                    "hint": "El resultado es: ",
                    "expression": "\\sqrt{3}"
                }
            ],
            "answers": [
                {
                    "answer": [
                        "\\sqrt{3}"
                    ],
                    "nextStep": "1"
                }
            ],
            "summary": "1) Se identifica el denominador radical.",
            "correctMsg": "Has identificado correctamente el denominador radical.",
            "validation": "evaluateAndCount",
            "incorrectMsg": "La expresión ingresada no es correcta.",
            "displayResult": [
                "\\frac{1}{\\sqrt{3}} \\longrightarrow \\sqrt{3}"
            ],
            "matchingError": [],
            "multipleChoice": [
                {
                    "id": 0,
                    "expression": "\\sqrt{3}",
                    "correct": true
                },
                {
                    "id": 1,
                    "expression": "3",
                    "correct": false,
                    "feedbackMsg": "Para racionalizar, necesitas identificar correctamente el denominador radical. Por ejemplo :",
                    "feedbackMsgExp": "\\frac{a}{\\sqrt{b}}\\longrightarrow \\sqrt{b}"
                },
                {
                    "id": 2,
                    "expression": "1",
                    "correct": false,
                    "feedbackMsg": "Para racionalizar, necesitas identificar correctamente el denominador radical. Por ejemplo :",
                    "feedbackMsgExp": "\\frac{a}{\\sqrt{b}}\\longrightarrow \\sqrt{b}"
                }
            ]
        },
        {
            "stepId": "1",
            "stepTitle": "Multiplica el numerador y el denominador por el denominador radical encontrado en el paso anterior.",
            "expression": "\\frac{1}{\\sqrt{3}} \\cdot \\frac{\\sqrt{3}}{\\sqrt{3}}",
            "KCs": [
                "IdeDenoRadi",
                "MultFrac",
                "SumDif"
            ],
            "hints": [
                {
                    "hintId": 0,
                    "hint": "Multiplica para poder eliminar la raíz del denominador."
                },
                {
                    "hintId": 1,
                    "hint": "El resultado es: ",
                    "expression": "\\frac{\\sqrt{3}}{3}"
                }
            ],
            "answers": [
                {
                    "answer": [
                        "\\frac{\\sqrt{3}}{3}"
                    ],
                    "nextStep": "-1"
                }
            ],
            "summary": "2) Se realiza la racionalización.",
            "correctMsg": "Has realizado correctamente la racionalización.",
            "validation": "evaluateAndCount",
            "incorrectMsg": "La expresión ingresada no es correcta.",
            "displayResult": [
                "\\frac{1}{\\sqrt{3}} \\cdot \\frac{\\sqrt{3}}{\\sqrt{3}} \\longrightarrow \\frac{\\sqrt{3}}{3}"
            ],
            "matchingError": [],
            "multipleChoice": [
                {
                    "id": 0,
                    "expression": "\\frac{\\sqrt{3}}{3}",
                    "correct": true
                },
                {
                    "id": 1,
                    "expression": "\\frac{\\sqrt{3}}{\\sqrt{3}}",
                    "correct": false,
                    "feedbackMsg": "Ten cuidado al multiplicar las raíces del denominador"
                },
                {
                    "id": 2,
                    "expression": "\\frac{1}{\\sqrt{3}}",
                    "correct": false,
                    "feedbackMsg": "Multiplica para poder eliminar la raíz del denominador."
                },
                {
                    "id": 3,
                    "expression": "\\frac{1}{3}",
                    "correct": false,
                    "feedbackMsg": "No te olvides que en el numerador también va",
                    "feedbackMsgExp": "\\sqrt{3}"
                }
            ]
        }
    ],
    "finalAnswer": {
        "stepId": "1",
        "stepTitle": "Multiplica el numerador y el denominador por el denominador radical encontrado en el paso anterior.",
        "expression": "\\frac{1}{\\sqrt{3}} \\cdot \\frac{\\sqrt{3}}{\\sqrt{3}}",
        "KCs": [
            "IdeDenoRadi",
            "MultFrac",
            "SumDif"
        ],
        "hints": [
            {
                "hintId": 0,
                "hint": "Multiplica para poder eliminar la raíz del denominador."
            },
            {
                "hintId": 1,
                "hint": "El resultado es: ",
                "expression": "\\frac{\\sqrt{3}}{3}"
            }
        ],
        "answers": [
            {
                "answer": [
                    "\\frac{\\sqrt{3}}{3}"
                ],
                "nextStep": "-1"
            }
        ],
        "summary": "2) Se realiza la racionalización.",
        "correctMsg": "Has realizado correctamente la racionalización.",
        "validation": "evaluateAndCount",
        "incorrectMsg": "La expresión ingresada no es correcta.",
        "displayResult": [
            "\\frac{1}{\\sqrt{3}} \\cdot \\frac{\\sqrt{3}}{\\sqrt{3}} \\longrightarrow \\frac{\\sqrt{3}}{3}"
        ],
        "matchingError": [],
        "multipleChoice": [
            {
                "id": 0,
                "expression": "\\frac{\\sqrt{3}}{3}",
                "correct": true
            },
            {
                "id": 1,
                "expression": "\\frac{\\sqrt{3}}{\\sqrt{3}}",
                "correct": false,
                "feedbackMsg": "Ten cuidado al multiplicar las raíces del denominador"
            },
            {
                "id": 2,
                "expression": "\\frac{1}{\\sqrt{3}}",
                "correct": false,
                "feedbackMsg": "Multiplica para poder eliminar la raíz del denominador."
            },
            {
                "id": 3,
                "expression": "\\frac{1}{3}",
                "correct": false,
                "feedbackMsg": "No te olvides que en el numerador también va",
                "feedbackMsgExp": "\\sqrt{3}"
            }
        ]
    }
}